{
  "oreGradeThresholds": {
    "high": 3.0,
    "medium": 2.0
  },
  "modelDefaults": {
    "opacity": 100,
    "visible": true
  },
  "highlightConfig": {
    "colorHex": "#ffff00",
    "durationMs": 1000
  },
  "boreholeConfig": {
    "colorHex": "#ff0000",
    "alpha": 0.8,
    "depthFailAlpha": 0.3,
    "width": 3,
    "markerImage": "/icons/borehole-marker.png",
    "markerSize": 24
  },
  "sectionConfig": {
    "colorHex": "#0000ff",
    "alpha": 0.7,
    "depthFailAlpha": 0.3,
    "width": 2
  },
  "defaultOreDensity": 2.5,
  "idPrefix": "feature_",
  "defaultCoordinates": {
    "wgs84": {
      "longitude": 116.39,
      "latitude": 39.9,
      "height": 100
    }
  }
}